LICENSE.txt
MANIFEST.in
README.md
setup.cfg
setup.py
planet_stack_finder.egg-info/PKG-INFO
planet_stack_finder.egg-info/SOURCES.txt
planet_stack_finder.egg-info/dependency_links.txt
planet_stack_finder.egg-info/entry_points.txt
planet_stack_finder.egg-info/not-zip-safe
planet_stack_finder.egg-info/requires.txt
planet_stack_finder.egg-info/top_level.txt
stackfinder/__init__.py
stackfinder/cli.py
stackfinder/geodetics.py