Metadata-Version: 1.1
Name: planet-stack-finder
Version: 0.0.9
Summary: Find local clusters from geojson.
Home-page: https://github.com/planetlabs/planet_stack_finder
Author: Josh Tennefoss
Author-email: jt@planet.com
License: MIT
Download-URL: https://github.com/planetlabs/planet_stack_finder/tarball/0.9
Keywords: stack_finder,planet,planet labs,overlaps
Platform: UNKNOWN
